{"images":[{"startdate":"20240903","fullstartdate":"202409030700","enddate":"20240904","url":"/th?id=OHR.AlpineLakes_EN-US9676616320_UHD.jpg&rf=LaDigue_UHD.jpg&pid=hp&w=3840&h=2160&rs=1&c=4","urlbase":"/th?id=OHR.AlpineLakes_EN-US9676616320","copyright":"Crystal Lake in the Enchantments, Alpine Lakes Wilderness, Washington (© Mitch Pittman/Tandem Stills + Motion)","copyrightlink":"/search?q=Wilderness+Act&form=hpcapt&filters=HpDate%3a%2220240903_0700%22","title":"Unspoiled beauty for all","caption":"Wilderness Act anniversary","copyrightonly":"© Mitch Pittman/Tandem Stills + Motion","desc":"Sometimes it's nice to get away. Thanks to environmentalist Howard Zahniser, Americans can do that in one of the country's many wildernesses—areas sheltered from human activities. While conservation efforts like the creation of national forests and parks began in the late 1800s, untamed wilderness had dwindled to only 2.5% of the nation's land by the 1960s. To reverse this trend, Zahniser wrote most of what became the Wilderness Act. Signed into law by President Lyndon Johnson on September 3, 1964, it today protects more than 109 million acres—5% of the land in the US.","date":"Sep 3, 2024","bsTitle":"Unspoiled beauty for all","quiz":"/search?q=Bing+homepage+quiz&filters=WQOskey:%22HPQuiz_20240903_AlpineLakes%22&FORM=HPQUIZ","wp":true,"hsh":"985ea5f8d2de09bdd06f9ed3a42368b2","drk":1,"top":1,"bot":1,"hs":[]}],"tooltips":{"loading":"Loading...","previous":"Previous image","next":"Next image","walle":"This image is not available to download as wallpaper.","walls":"Download this image. Use of this image is restricted to wallpaper only."}}